unitycatalog/ai/gemini/__init__.py
unitycatalog/ai/gemini/toolkit.py
unitycatalog/ai/gemini/utils.py
unitycatalog/ai/gemini/version.py
unitycatalog_gemini-0.2.0.dist-info/METADATA
unitycatalog_gemini-0.2.0.dist-info/WHEEL
unitycatalog_gemini-0.2.0.dist-info/RECORD
